huggingface_sb3/__init__.py
huggingface_sb3/load_from_hub.py
huggingface_sb3/naming_schemes.py
huggingface_sb3/push_to_hub.py
huggingface_sb3-3.0.dist-info/METADATA
huggingface_sb3-3.0.dist-info/WHEEL
huggingface_sb3-3.0.dist-info/top_level.txt
huggingface_sb3-3.0.dist-info/RECORD
