Metadata-Version: 2.1
Name: huggingface_sb3
Version: 3.0
Summary: Additional code for Stable-baselines3 to load and upload models from the Hub.
Home-page: https://github.com/huggingface/huggingface_sb3
Author: Thomas Simonini, Omar Sanseviero and Hugging Face Team
Author-email: thomas.simonini@huggingface.co
License: Apache
Keywords: reinforcement learning deep reinforcement learning RL
Platform: UNKNOWN
Provides-Extra: quality
